acmax24/.__init__.py.swp
acmax24/__init__.py
acmax24-0.2.7.dist-info/LICENSE
acmax24-0.2.7.dist-info/METADATA
acmax24-0.2.7.dist-info/WHEEL
acmax24-0.2.7.dist-info/RECORD
